README.rst
setup.py
djbraintree/__init__.py
djbraintree/context_processors.py
djbraintree/models.py
djbraintree.egg-info/PKG-INFO
djbraintree.egg-info/SOURCES.txt
djbraintree.egg-info/dependency_links.txt
djbraintree.egg-info/not-zip-safe
djbraintree.egg-info/requires.txt
djbraintree.egg-info/top_level.txt