Metadata-Version: 1.0
Name: djbraintree
Version: 0.1.0
Summary: Braintree for Django
Home-page: https://github.com/iconfinder/djbraintree
Author: Nick Bruun <nick@bruun.co>
Author-email: nick@bruun.co
License: BSD License
Keywords: django,braintree
Platform: UNKNOWN
Classifier: Programming Language :: Python
Classifier: Programming Language :: Python :: 2.6
Classifier: Programming Language :: Python :: 2.7
Classifier: Programming Language :: Python :: 3
Classifier: Programming Language :: Python :: 3.2
Classifier: License :: OSI Approved :: BSD License
Classifier: Topic :: Software Development :: Libraries :: Python Modules
Classifier: Framework :: Django
Classifier: Environment :: Web Environment
